CrawlerFriend/__init__.py
CrawlerFriend-1.0.11.dist-info/METADATA
CrawlerFriend-1.0.11.dist-info/RECORD
CrawlerFriend-1.0.11.dist-info/WHEEL
CrawlerFriend-1.0.11.dist-info/top_level.txt
