Metadata-Version: 2.1
Name: CrawlerFriend
Version: 1.0.11
Summary: A light weight crawler which gives search results in HTML form or in Dictionary form, given urls and keywords.
Home-page: https://github.com/Sreejoy/CrawlerFriend
Author: Sreejoy Halder
Author-email: sreejoy4242@gmail.com
License: UNKNOWN
Platform: UNKNOWN
Classifier: Programming Language :: Python :: 2.7
Classifier: License :: OSI Approved :: MIT License
Classifier: Operating System :: OS Independent
Requires-Dist: requests
Requires-Dist: beautifulsoup4
